kimmdy_dimerization/__init__.py
kimmdy_dimerization/kimmdy-yaml-schema.json
kimmdy_dimerization/reaction.py
kimmdy_dimerization/data/new_charges.json
kimmdy_dimerization-0.2.0.dist-info/licenses/LICENSE
kimmdy_dimerization-0.2.0.dist-info/METADATA
kimmdy_dimerization-0.2.0.dist-info/WHEEL
kimmdy_dimerization-0.2.0.dist-info/entry_points.txt
kimmdy_dimerization-0.2.0.dist-info/top_level.txt
kimmdy_dimerization-0.2.0.dist-info/RECORD
