Metadata-Version: 2.4
Name: kimmdy-dimerization
Version: 0.2.0
Summary: Reaction plugin for KIMMDY describing the dimerization of thymines in DNA
Author-email: Boris Schuepp <boris.schuepp@mpip-mainz.mpg.de>
License: GPL-3.0
Classifier: Programming Language :: Python :: 3
Classifier: Operating System :: OS Independent
Requires-Python: >=3.10
License-File: LICENSE
Requires-Dist: MDAnalysis
Requires-Dist: kimmdy
Dynamic: license-file
